exclusive/__init__.py
exclusive/exclusive.py
exclusive-0.3.0.dist-info/LICENSE
exclusive-0.3.0.dist-info/METADATA
exclusive-0.3.0.dist-info/WHEEL
exclusive-0.3.0.dist-info/top_level.txt
exclusive-0.3.0.dist-info/RECORD
